doc_calculator/__init__.py
doc_calculator/core/DOC_Calculator.py
doc_calculator/core/__init__.py
doc_calculator/core/utils/__init__.py
doc_calculator/core/utils/params.py
doc_calculator/core/utils/util_functions.py
doc_calculator/gemseo_discipline/DOC_Calculator.py
doc_calculator/gemseo_discipline/__init__.py
doc_calculator/gemseo_discipline/utils/__init__.py
doc_calculator/gemseo_discipline/utils/utils_functions.py
doc_calculator-0.5.0.dist-info/LICENSE
doc_calculator-0.5.0.dist-info/METADATA
doc_calculator-0.5.0.dist-info/WHEEL
doc_calculator-0.5.0.dist-info/top_level.txt
doc_calculator-0.5.0.dist-info/RECORD
