Metadata-Version: 2.2
Name: doc_calculator
Version: 0.5.0
License-File: LICENSE
Requires-Dist: gemseo
Dynamic: description
Dynamic: description-content-type
Dynamic: requires-dist
